xia_engine_test/__init__.py
xia_engine_test/document_example.cpython-310-darwin.so
xia_engine_test/field_test.cpython-310-darwin.so
xia_engine_test/models.cpython-310-darwin.so
xia_engine_test-0.1.6.dist-info/LICENSE.txt
xia_engine_test-0.1.6.dist-info/METADATA
xia_engine_test-0.1.6.dist-info/WHEEL
xia_engine_test-0.1.6.dist-info/top_level.txt
xia_engine_test-0.1.6.dist-info/RECORD
